LICENSE
README.md
named_locks/__init__.py
named_locks/async_named_lock.py
named_locks/base_named_lock.py
namedlocks-0.0.1a3.dist-info/METADATA
namedlocks-0.0.1a3.dist-info/WHEEL
namedlocks-0.0.1a3.dist-info/licenses/LICENSE
namedlocks-0.0.1a3.dist-info/RECORD
