Metadata-Version: 2.1
Name: namedlocks
Version: 0.0.1a3
Summary: Named Locks to acquire lock by name
Project-URL: Homepage, https://github.com/andrew000/NamedLocks
Project-URL: Bug Tracker, https://github.com/andrew000/named_lock/issues
Author: Andrew King
License: MIT License
License-File: LICENSE
Classifier: Development Status :: 3 - Alpha
Classifier: License :: OSI Approved :: MIT License
Classifier: Operating System :: OS Independent
Requires-Python: >=3.9
